winrm/__init__.py
winrm/encryption.py
winrm/exceptions.py
winrm/protocol.py
winrm/transport.py
winrm/tests/__init__.py
winrm/tests/conftest.py
winrm/tests/sample_script.ps1
winrm/tests/test_cmd.py
winrm/tests/test_encryption.py
winrm/tests/test_integration_protocol.py
winrm/tests/test_integration_session.py
winrm/tests/test_nori_type_casting.py
winrm/tests/test_powershell.py
winrm/tests/test_protocol.py
winrm/tests/test_session.py
winrm/tests/test_transport.py
winrm/tests/test_wql.py
winrm/vendor/__init__.py
winrm/vendor/requests_kerberos/__init__.py
winrm/vendor/requests_kerberos/compat.py
winrm/vendor/requests_kerberos/exceptions.py
winrm/vendor/requests_kerberos/kerberos_.py
cloudchef_pywinrm-0.4.2.dist-info/LICENSE
cloudchef_pywinrm-0.4.2.dist-info/METADATA
cloudchef_pywinrm-0.4.2.dist-info/WHEEL
cloudchef_pywinrm-0.4.2.dist-info/top_level.txt
cloudchef_pywinrm-0.4.2.dist-info/RECORD
