Metadata-Version: 2.1
Name: cloudchef-pywinrm
Version: 0.4.2
Summary: Python library for Windows Remote Management
Home-page: http://github.com/diyan/pywinrm/
Author: Alexey Diyan
Author-email: alexey.diyan@gmail.com
License: MIT license
Keywords: winrm,ws-man,devops,ws-management
Platform: UNKNOWN
Classifier: Development Status :: 4 - Beta
Classifier: Environment :: Console
Classifier: Intended Audience :: Developers
Classifier: Intended Audience :: System Administrators
Classifier: Natural Language :: English
Classifier: License :: OSI Approved :: MIT License
Classifier: Programming Language :: Python
Classifier: Programming Language :: Python :: 2
Classifier: Programming Language :: Python :: 2.7
Classifier: Programming Language :: Python :: 3
Classifier: Programming Language :: Python :: 3.5
Classifier: Programming Language :: Python :: 3.6
Classifier: Programming Language :: Python :: 3.7
Classifier: Programming Language :: Python :: 3.8
Classifier: Programming Language :: Python :: Implementation :: PyPy
Classifier: Topic :: Software Development :: Libraries :: Python Modules
Classifier: Topic :: System :: Clustering
Classifier: Topic :: System :: Distributed Computing
Classifier: Topic :: System :: Systems Administration
Requires-Dist: xmltodict
Requires-Dist: requests (>=2.9.1)
Requires-Dist: requests-ntlm (>=0.3.0)
Requires-Dist: six
Provides-Extra: credssp
Requires-Dist: requests-credssp (>=1.0.0) ; extra == 'credssp'
Provides-Extra: kerberos
Requires-Dist: pykerberos (<2.0.0,>=1.2.1) ; (sys_platform!="win32") and extra == 'kerberos'
Requires-Dist: winkerberos (>=0.5.0) ; (sys_platform=="win32") and extra == 'kerberos'
